odoo/addons/pos_meal_voucher/README.rst
odoo/addons/pos_meal_voucher/__init__.py
odoo/addons/pos_meal_voucher/__manifest__.py
odoo/addons/pos_meal_voucher/data/barcode_rule.xml
odoo/addons/pos_meal_voucher/demo/product_category.xml
odoo/addons/pos_meal_voucher/demo/product_product.xml
odoo/addons/pos_meal_voucher/i18n/fr.po
odoo/addons/pos_meal_voucher/i18n/it.po
odoo/addons/pos_meal_voucher/i18n/pos_meal_voucher.pot
odoo/addons/pos_meal_voucher/models/__init__.py
odoo/addons/pos_meal_voucher/models/barcode_rule.py
odoo/addons/pos_meal_voucher/models/pos_config.py
odoo/addons/pos_meal_voucher/models/pos_order.py
odoo/addons/pos_meal_voucher/models/pos_payment_method.py
odoo/addons/pos_meal_voucher/models/pos_session.py
odoo/addons/pos_meal_voucher/models/product_category.py
odoo/addons/pos_meal_voucher/models/product_product.py
odoo/addons/pos_meal_voucher/models/product_template.py
odoo/addons/pos_meal_voucher/models/res_config_settings.py
odoo/addons/pos_meal_voucher/readme/CONFIGURE.rst
odoo/addons/pos_meal_voucher/readme/CONTRIBUTORS.rst
odoo/addons/pos_meal_voucher/readme/CREDITS.rst
odoo/addons/pos_meal_voucher/readme/DESCRIPTION.rst
odoo/addons/pos_meal_voucher/readme/ROADMAP.rst
odoo/addons/pos_meal_voucher/readme/USAGE.rst
odoo/addons/pos_meal_voucher/static/description/icon.png
odoo/addons/pos_meal_voucher/static/description/index.html
odoo/addons/pos_meal_voucher/static/description/issuer_1_up_dejeuner.jpg
odoo/addons/pos_meal_voucher/static/description/issuer_2_ticket_restaurant.jpeg
odoo/addons/pos_meal_voucher/static/description/issuer_3_apetiz.png
odoo/addons/pos_meal_voucher/static/description/issuer_4_pass_restaurant.png
odoo/addons/pos_meal_voucher/static/description/pos_order_screen.png
odoo/addons/pos_meal_voucher/static/description/pos_payment_method_form.png
odoo/addons/pos_meal_voucher/static/description/pos_payment_screen_meal_vouchers.png
odoo/addons/pos_meal_voucher/static/description/pos_payment_screen_warning.png
odoo_addon_pos_meal_voucher-16.0.1.0.0.4.dist-info/METADATA
odoo_addon_pos_meal_voucher-16.0.1.0.0.4.dist-info/WHEEL
odoo_addon_pos_meal_voucher-16.0.1.0.0.4.dist-info/top_level.txt
odoo_addon_pos_meal_voucher-16.0.1.0.0.4.dist-info/RECORD
